LICENSE
falcon_compression/__init__.py
falcon_compression/brotli.py
falcon_compression/gzip.py
falcon_compression/middleware.py
falcon_compression/util.py
falcon_compression-0.2.1.dist-info/LICENSE
falcon_compression-0.2.1.dist-info/WHEEL
falcon_compression-0.2.1.dist-info/METADATA
falcon_compression-0.2.1.dist-info/RECORD
